{
  "id": "registry-relay-provenance-v1",
  "uri": "https://id.registrystack.org/ns/registry-relay/provenance/v1#",
  "title": "Registry Relay provenance v1 namespace",
  "description": "JSON-LD namespace for Registry Relay provenance credential terms.",
  "kind": "namespace",
  "documented_by": [
    {
      "title": "Contracts and machine identifiers",
      "href": "https://docs.registrystack.org/reference/contracts/"
    },
    {
      "title": "Registry Relay product docs",
      "href": "https://docs.registrystack.org/products/registry-relay/"
    },
    {
      "title": "Registry Relay API overview",
      "href": "https://docs.registrystack.org/reference/apis/registry-relay/"
    },
    {
      "title": "Registry Stack documentation",
      "href": "https://docs.registrystack.org/"
    }
  ],
  "authority": {
    "scope": "identifier metadata",
    "statement": "This site identifies stable Registry Stack identifiers and links to public documentation. Product documentation, published schemas, and the actual service response remain authoritative for runtime behavior."
  }
}
